chaotic_exceptions/__init__.py
chaotic_exceptions/chaos.py
chaotic_exceptions/exceptions.py
chaotic_exceptions-0.0.1.dist-info/licenses/LICENCE
chaotic_exceptions-0.0.1.dist-info/METADATA
chaotic_exceptions-0.0.1.dist-info/WHEEL
chaotic_exceptions-0.0.1.dist-info/top_level.txt
chaotic_exceptions-0.0.1.dist-info/RECORD
