Metadata-Version: 2.4
Name: chaotic-exceptions
Version: 0.0.1
Summary: A library for generating random exceptions to test system resilience
Home-page: https://github.com/yourusername/chaotic-exceptions
Author: Your Name
Author-email: Paulius Klyvis <paul@algorithmic.space>
Project-URL: Homepage, https://github.com/grafke/chaotic-exceptions
Project-URL: Bug Reports, https://github.com/grafke/chaotic-exceptions/issues
Project-URL: Source, https://github.com/grafke/chaotic-exceptions
Keywords: testing,chaos,exception,resilience,fault-injection
Classifier: Development Status :: 4 - Beta
Classifier: Intended Audience :: Developers
Classifier: Topic :: Software Development :: Testing
Classifier: Topic :: Software Development :: Quality Assurance
Classifier: License :: OSI Approved :: MIT License
Classifier: Programming Language :: Python :: 3
Classifier: Programming Language :: Python :: 3.7
Classifier: Programming Language :: Python :: 3.8
Classifier: Programming Language :: Python :: 3.9
Classifier: Programming Language :: Python :: 3.10
Classifier: Programming Language :: Python :: 3.11
Classifier: Programming Language :: Python :: 3.12
Requires-Python: >=3.7
License-File: LICENCE
Dynamic: author
Dynamic: home-page
Dynamic: license-file
Dynamic: requires-python
